fourinsight/campaigns/__init__.py
fourinsight/campaigns/api.py
fourinsight/campaigns/campaign.py
fourinsight/campaigns/channels.py
fourinsight/campaigns/client.py
fourinsight/campaigns/utils.py
fourinsight_campaigns-0.2.10.dist-info/METADATA
fourinsight_campaigns-0.2.10.dist-info/WHEEL
fourinsight_campaigns-0.2.10.dist-info/top_level.txt
fourinsight_campaigns-0.2.10.dist-info/RECORD
