Metadata-Version: 2.4
Name: fourinsight-campaigns
Version: 0.2.10
Summary: 4insight campaigns
Home-page: https://4insight.io
Author: 4Subsea
Author-email: support@4subsea.com
Project-URL: Documentation, https://docs.4insight.io/campaigns/python/latest
Classifier: License :: OSI Approved :: MIT License
Classifier: Operating System :: OS Independent
Classifier: Programming Language :: Python :: 3.11
Classifier: Programming Language :: Python :: 3.12
Classifier: Programming Language :: Python :: 3.13
Requires-Python: >=3.11
Requires-Dist: fourinsight-api
Requires-Dist: pandas
Requires-Dist: numpy
